LICENSE
README.md
setup.py
scPAFA/__init__.py
scPAFA/config.py
scPAFA.egg-info/PKG-INFO
scPAFA.egg-info/SOURCES.txt
scPAFA.egg-info/dependency_links.txt
scPAFA.egg-info/requires.txt
scPAFA.egg-info/top_level.txt
scPAFA/_plot/__init__.py
scPAFA/_plot/_plot_function.py
scPAFA/_pseudobulk/_Dict.py
scPAFA/_pseudobulk/_Mofa.py
scPAFA/_pseudobulk/__init__.py
scPAFA/_stat/__init__.py
scPAFA/_stat/_stat_function.py
scPAFA/_tools/__init__.py
scPAFA/_tools/_fast_UCell.py
scPAFA/_tools/_fast_score_genes.py
scPAFA/_tools/_pathway_dict.py
scPAFA/build_model/__init__.py
scPAFA/build_model/build_model.py
scPAFA/build_model/init_model.py
scPAFA/build_model/save_model.py
scPAFA/build_model/train_model.py
scPAFA/build_model/utils.py
scPAFA/core/BayesNet.py
scPAFA/core/__init__.py
scPAFA/core/gp_utils.py
scPAFA/core/gpu_utils.py
scPAFA/core/utils.py
scPAFA/core/distributions/__init__.py
scPAFA/core/distributions/basic_distributions.py
scPAFA/core/distributions/bernoulli.py
scPAFA/core/distributions/bernoulli_gaussian.py
scPAFA/core/distributions/beta.py
scPAFA/core/distributions/binomial.py
scPAFA/core/distributions/gamma.py
scPAFA/core/distributions/multi_task_GP.py
scPAFA/core/distributions/multivariate_gaussian.py
scPAFA/core/distributions/poisson.py
scPAFA/core/distributions/univariate_gaussian.py
scPAFA/core/nodes/Alpha_nodes.py
scPAFA/core/nodes/Kc_node.py
scPAFA/core/nodes/Kg_node.py
scPAFA/core/nodes/Sigma_node.py
scPAFA/core/nodes/Tau_nodes.py
scPAFA/core/nodes/Theta_nodes.py
scPAFA/core/nodes/U_nodes.py
scPAFA/core/nodes/W_nodes.py
scPAFA/core/nodes/Y_nodes.py
scPAFA/core/nodes/Z_nodes.py
scPAFA/core/nodes/Z_nodes_GP.py
scPAFA/core/nodes/Z_nodes_GP_mv.py
scPAFA/core/nodes/ZgU_node.py
scPAFA/core/nodes/__init__.py
scPAFA/core/nodes/basic_nodes.py
scPAFA/core/nodes/multiview_nodes.py
scPAFA/core/nodes/nongaussian_nodes.py
scPAFA/core/nodes/variational_nodes.py
scPAFA/run/__init__.py
scPAFA/run/entry_point.py
scPAFA/simulate/__init__.py
scPAFA/simulate/simulate_mofa.py