Metadata-Version: 2.1
Name: scPAFA
Version: 0.1.3
Summary: Single Cell Pathway Activity Factor Analysis
Home-page: https://github.com/ZhuoliHuang/scPAFA
Author: Zhuoli Huang
Author-email: bioagr_huangzl@163.com
License: GPL-3.0
License-File: LICENSE
Requires-Dist: scanpy>=1.9.0
Requires-Dist: anndata>=0.9.0
Requires-Dist: mofax==0.3.6
Requires-Dist: pandas>=2.0.3
Requires-Dist: scipy==1.11.3
Requires-Dist: plotnine
Requires-Dist: statsmodels
Requires-Dist: pathos
Requires-Dist: tqdm
Requires-Dist: nheatmap
Requires-Dist: seaborn
